sprockets.mixins.http-2.6.0-py3.9-nspkg.pth
sprockets/mixins/http/__init__.py
sprockets.mixins.http-2.6.0.dist-info/LICENSE
sprockets.mixins.http-2.6.0.dist-info/METADATA
sprockets.mixins.http-2.6.0.dist-info/WHEEL
sprockets.mixins.http-2.6.0.dist-info/namespace_packages.txt
sprockets.mixins.http-2.6.0.dist-info/top_level.txt
sprockets.mixins.http-2.6.0.dist-info/zip-safe
sprockets.mixins.http-2.6.0.dist-info/RECORD
