Metadata-Version: 2.1
Name: sprockets.mixins.http
Version: 2.6.0
Summary: HTTP Client Mixin for Tornado RequestHandlers
Home-page: https://github.com/sprockets/sprockets.mixins.http
Author: AWeber Communications, Inc.
Author-email: api@aweber.com
License: BSD
Platform: UNKNOWN
Classifier: Development Status :: 5 - Production/Stable
Classifier: Intended Audience :: Developers
Classifier: License :: OSI Approved :: BSD License
Classifier: Natural Language :: English
Classifier: Operating System :: OS Independent
Classifier: Programming Language :: Python :: 3.7
Classifier: Programming Language :: Python :: 3.8
Classifier: Programming Language :: Python :: 3.9
Classifier: Programming Language :: Python :: Implementation :: CPython
Classifier: Topic :: Software Development :: Libraries
Classifier: Topic :: Software Development :: Libraries :: Python Modules
Requires-Python: >=3.7
License-File: LICENSE
Requires-Dist: ietfparse (>=1.5.1)
Requires-Dist: sprockets.mixins.mediatype[msgpack] (>=3.0.0)
Requires-Dist: tornado (>=5)
Provides-Extra: curl
Requires-Dist: pycurl ; extra == 'curl'
